sheildantic/__init__.py
sheildantic/core.py
sheildantic/fastapi.py
sheildantic/models.py
sheildantic-0.1.0.dist-info/METADATA
sheildantic-0.1.0.dist-info/WHEEL
sheildantic-0.1.0.dist-info/RECORD
