Metadata-Version: 2.3
Name: sheildantic
Version: 0.1.0
Summary: A robust data validation and serialization library built on top of Pydantic
License: MIT
Keywords: validation,serialization,pydantic,data
Author: Ahmad
Requires-Python: >=3.12
Classifier: Development Status :: 3 - Alpha
Classifier: Intended Audience :: Developers
Classifier: License :: OSI Approved :: MIT License
Classifier: Programming Language :: Python :: 3
Classifier: Programming Language :: Python :: 3.12
Classifier: Topic :: Software Development :: Libraries :: Python Modules
Requires-Dist: anyio (>=4.8.0)
Requires-Dist: fastapi (>=0.115.8)
Requires-Dist: httpx (>=0.28.1)
Requires-Dist: multidict (>=6.1.0)
Requires-Dist: nh3 (>=0.2.20)
Requires-Dist: pydantic (>=2.5.3)
Project-URL: Issues, https://github.com/Hybridhash/Sheildantic/issues
Project-URL: Repository, https://github.com/Hybridhash/Sheildantic
